ayaka/__init__.py
ayaka/adapters/__init__.py
ayaka/adapters/adapter.py
ayaka/adapters/console.py
ayaka/adapters/gocq.py
ayaka/adapters/nb1/hoshino.py
ayaka/adapters/nb1/nb1.py
ayaka/adapters/nb2/ob11.py
ayaka/adapters/nb2/qqguild_patch.py
ayaka/cat.py
ayaka/config.py
ayaka/context.py
ayaka/database.py
ayaka/download.py
ayaka/exception.py
ayaka/logger.py
ayaka/master.py
ayaka/playwright.py
ayaka/session.py
ayaka/subscribe.py
ayaka/trigger.py
ayaka-0.0.4.7.dist-info/LICENSE
ayaka-0.0.4.7.dist-info/METADATA
ayaka-0.0.4.7.dist-info/WHEEL
ayaka-0.0.4.7.dist-info/RECORD
