Metadata-Version: 2.1
Name: ayaka
Version: 0.0.4.7
Summary: 猫猫，猫猫！
Home-page: https://bridgel.github.io/ayaka/
License: MIT
Author: Su
Author-email: wxlxy316@163.com
Requires-Python: >=3.10,<4.0
Classifier: License :: OSI Approved :: MIT License
Classifier: Programming Language :: Python :: 3
Classifier: Programming Language :: Python :: 3.10
Classifier: Programming Language :: Python :: 3.11
Provides-Extra: fastapi
Provides-Extra: nb2ob11
Provides-Extra: playwright
Requires-Dist: ayaka-db (>=0.0.3)
Requires-Dist: ayaka-utils (>=0.0.4)
Requires-Dist: fastapi (>=0.87.0,!=0.89.0,<1.0.0) ; extra == "fastapi"
Requires-Dist: httpx (>=0.20.0,<1.0.0)
Requires-Dist: nonebot-adapter-onebot (>=2.2.0) ; extra == "nb2ob11"
Requires-Dist: nonebot2 (>=2.0.0b5) ; extra == "nb2ob11"
Requires-Dist: playwright (>=1.17.2) ; extra == "playwright"
Requires-Dist: pydantic (>=1.10.0)
Requires-Dist: uvicorn[standard] (>=0.20.0,<1.0.0) ; extra == "fastapi"
Project-URL: Repository, https://github.com/bridgeL/ayaka
